codn/__init__.py
codn/cli.py
codn/cli_commands/__init__.py
codn/cli_commands/analyze_cli.py
codn/cli_commands/git_cli.py
codn/cli_commands/lsp_cli.py
codn/utils/__init__.py
codn/utils/base_lsp_client.py
codn/utils/git_utils.py
codn/utils/lsp_utils.py
codn/utils/os_utils.py
codn/utils/simple_ast.py
codn-0.1.5.dist-info/licenses/LICENSE
codn-0.1.5.dist-info/METADATA
codn-0.1.5.dist-info/WHEEL
codn-0.1.5.dist-info/entry_points.txt
codn-0.1.5.dist-info/top_level.txt
codn-0.1.5.dist-info/RECORD
