Metadata-Version: 2.4
Name: codn
Version: 0.1.5
Summary: A tiny, modular library for common coding tasks.
Author-email: askender <askender43@gmail.com>
License-Expression: MIT
Project-URL: Homepage, https://github.com/dweb-lab/codn
Requires-Python: >=3.8
License-File: LICENSE
Requires-Dist: typer
Requires-Dist: watchfiles
Requires-Dist: pathspec
Requires-Dist: loguru
Requires-Dist: rich
Dynamic: license-file
